[
  {
    "id": "211e4567-e89b-12d3-a456-426614174000",
    "name": "Laptop Pro 14",
    "description": "High performance laptop with 16GB RAM",
    "price": "1499.99",
    "inventoryCount": "50"
  },
  {
    "id": "211e4567-e89b-12d3-a456-426614174001",
    "name": "Wireless Mouse",
    "description": "Ergonomic wireless mouse with adjustable DPI",
    "price": "39.99",
    "inventoryCount": "200"
  },
  {
    "id": "211e4567-e89b-12d3-a456-426614174002",
    "name": "Mechanical Keyboard",
    "description": "RGB mechanical keyboard with blue switches",
    "price": "89.99",
    "inventoryCount": "120"
  },
  {
    "id": "211e4567-e89b-12d3-a456-426614174003",
    "name": "27\" 4K Monitor",
    "description": "Ultra HD monitor with HDR10 support",
    "price": "399.99",
    "inventoryCount": "75"
  },
  {
    "id": "211e4567-e89b-12d3-a456-426614174004",
    "name": "Gaming Chair",
    "description": "Ergonomic chair with lumbar support and adjustable height",
    "price": "199.99",
    "inventoryCount": "60"
  },
  {
    "id": "211e4567-e89b-12d3-a456-426614174005",
    "name": "External SSD 1TB",
    "description": "Portable SSD with USB-C connectivity",
    "price": "129.99",
    "inventoryCount": "150"
  },
  {
    "id": "211e4567-e89b-12d3-a456-426614174006",
    "name": "Smartphone X",
    "description": "Latest generation smartphone with OLED display",
    "price": "999.99",
    "inventoryCount": "80"
  },
  {
    "id": "211e4567-e89b-12d3-a456-426614174007",
    "name": "Wireless Earbuds",
    "description": "Noise-cancelling earbuds with 24h battery life",
    "price": "149.99",
    "inventoryCount": "300"
  },
  {
    "id": "211e4567-e89b-12d3-a456-426614174008",
    "name": "Smartwatch Z",
    "description": "Fitness smartwatch with heart rate and sleep tracking",
    "price": "249.99",
    "inventoryCount": "90"
  },
  {
    "id": "211e4567-e89b-12d3-a456-426614174009",
    "name": "Bluetooth Speaker",
    "description": "Portable waterproof Bluetooth speaker",
    "price": "79.99",
    "inventoryCount": "200"
  },
  {
    "id": "211e4567-e89b-12d3-a456-426614174010",
    "name": "Drone Pro",
    "description": "4K camera drone with GPS and obstacle avoidance",
    "price": "599.99",
    "inventoryCount": "40"
  },
  {
    "id": "211e4567-e89b-12d3-a456-426614174011",
    "name": "Action Camera",
    "description": "Waterproof action camera with 4K recording",
    "price": "199.99",
    "inventoryCount": "70"
  },
  {
    "id": "211e4567-e89b-12d3-a456-426614174012",
    "name": "Router AX3000",
    "description": "Dual-band WiFi 6 router with high-speed coverage",
    "price": "129.99",
    "inventoryCount": "110"
  },
  {
    "id": "211e4567-e89b-12d3-a456-426614174013",
    "name": "Smart Home Hub",
    "description": "Central hub for smart home devices",
    "price": "149.99",
    "inventoryCount": "85"
  },
  {
    "id": "211e4567-e89b-12d3-a456-426614174014",
    "name": "Electric Scooter",
    "description": "Foldable electric scooter with 20km range",
    "price": "499.99",
    "inventoryCount": "30"
  }
]